gs_reminder/__init__.py
gs_reminder/__main__.py
gs_reminder/bridge.py
gs_reminder/error.py
gs_reminder/github/__init__.py
gs_reminder/github/api.py
gs_reminder/github/models/__init__.py
gs_reminder/github/models/pull_request.py
gs_reminder/github/models/user.py
gs_reminder/notifier.py
gs_reminder/py.typed
gs_reminder/slack/__init__.py
gs_reminder/slack/api.py
gs_reminder-0.5.3.dist-info/LICENSE
gs_reminder-0.5.3.dist-info/METADATA
gs_reminder-0.5.3.dist-info/WHEEL
gs_reminder-0.5.3.dist-info/entry_points.txt
gs_reminder-0.5.3.dist-info/RECORD
