Metadata-Version: 2.1
Name: gs-reminder
Version: 0.5.3
Summary: Notify Slack of a review of Pull Requests in the GitHub repository.
Home-page: https://github.com/nnsnodnb/gs-reminder
License: MIT
Author: Yuya Oka
Author-email: nnsnodnb@gmail.com
Requires-Python: >=3.9,<3.14
Classifier: License :: OSI Approved :: MIT License
Classifier: Programming Language :: Python :: 3
Classifier: Programming Language :: Python :: 3.9
Classifier: Programming Language :: Python :: 3.10
Classifier: Programming Language :: Python :: 3.11
Classifier: Programming Language :: Python :: 3.12
Classifier: Programming Language :: Python :: 3.13
Requires-Dist: click (>=8.1.3,<9.0.0)
Requires-Dist: pydantic (>=2.9.2)
Requires-Dist: requests (>=2.32.3,<3.0.0)
Project-URL: Repository, https://github.com/nnsnodnb/gs-reminder
